fro/__init__.py
fro/_implementation/__init__.py
fro/_implementation/boxed_value.py
fro/_implementation/iters.py
fro/_implementation/location.py
fro/_implementation/parse_error.py
fro/_implementation/parser.py
fro/_implementation/pretty_printing.py
fro/_implementation/chompers/__init__.py
fro/_implementation/chompers/abstract.py
fro/_implementation/chompers/alternation.py
fro/_implementation/chompers/box.py
fro/_implementation/chompers/chomp_error.py
fro/_implementation/chompers/composition.py
fro/_implementation/chompers/nested.py
fro/_implementation/chompers/regex.py
fro/_implementation/chompers/sequence.py
fro/_implementation/chompers/state.py
fro/_implementation/chompers/until.py
fro/_implementation/chompers/util.py
fro-2.0.0.dist-info/DESCRIPTION.rst
fro-2.0.0.dist-info/METADATA
fro-2.0.0.dist-info/RECORD
fro-2.0.0.dist-info/WHEEL
fro-2.0.0.dist-info/metadata.json
fro-2.0.0.dist-info/top_level.txt
