Metadata-Version: 2.0
Name: fro
Version: 2.0.0
Summary: A module for parsing string representations of objects
Home-page: https://github.com/ethantkoenig/fro
Author: Ethan Koenig
Author-email: ethantkoenig@gmail.com
License: MIT
Keywords: fro parsing object representations
Platform: UNKNOWN
Classifier: License :: OSI Approved :: MIT License
Classifier: Programming Language :: Python :: 2.7
Classifier: Programming Language :: Python :: 3
Classifier: Programming Language :: Python :: 3.2
Classifier: Programming Language :: Python :: 3.3
Classifier: Programming Language :: Python :: 3.4
Requires-Dist: future
